sprockets_influxdb.py
sprockets_influxdb-2.2.1.dist-info/LICENSE
sprockets_influxdb-2.2.1.dist-info/METADATA
sprockets_influxdb-2.2.1.dist-info/WHEEL
sprockets_influxdb-2.2.1.dist-info/top_level.txt
sprockets_influxdb-2.2.1.dist-info/zip-safe
sprockets_influxdb-2.2.1.dist-info/RECORD
